README.rst
setup.cfg
setup.py
pyglib/__init__.py
pyglib/app.py
pyglib/helpflags.py
pyglib.egg-info/PKG-INFO
pyglib.egg-info/SOURCES.txt
pyglib.egg-info/dependency_links.txt
pyglib.egg-info/requires.txt
pyglib.egg-info/top_level.txt