Metadata-Version: 1.1
Name: pyglib
Version: 0.1
Summary: Opinionated but handy app startup wrapper.
Home-page: https://github.com/benley/pyglib
Author: Benjamin Staffin
Author-email: benley@gmail.com
License: BSD
Platform: any
Classifier: Programming Language :: Python
Classifier: Development Status :: 4 - Beta
Classifier: Intended Audience :: Developers
Classifier: License :: OSI Approved :: BSD License
Classifier: Topic :: System :: Logging
Classifier: Topic :: Software Development :: Libraries :: Python Modules
